{
  "$schema": "https://json-schema.org/draft/2020-12/schema",
  "$id": "https://getrapidkit.com/schemas/workspace-model-snapshot.v1.json",
  "title": "RapidKit Workspace Model Snapshot",
  "type": "object",
  "required": ["schemaVersion", "generatedAt", "modelHash", "modelRef", "model"],
  "properties": {
    "schemaVersion": {
      "const": "workspace-model-snapshot.v1"
    },
    "generatedAt": {
      "type": "string",
      "format": "date-time"
    },
    "modelHash": {
      "type": "string",
      "minLength": 64,
      "maxLength": 64
    },
    "modelRef": {
      "type": "string",
      "minLength": 1
    },
    "model": {
      "type": "object",
      "required": ["schemaVersion"],
      "properties": {
        "schemaVersion": {
          "const": "workspace-model.v1"
        }
      },
      "additionalProperties": true
    }
  },
  "additionalProperties": true
}
